jdMinecraftLauncher/AccountManager.py
jdMinecraftLauncher/Constants.py
jdMinecraftLauncher/DBusInterface.xml
jdMinecraftLauncher/DBusService.py
jdMinecraftLauncher/Distribution.toml
jdMinecraftLauncher/Environment.py
jdMinecraftLauncher/Functions.py
jdMinecraftLauncher/Icon.svg
jdMinecraftLauncher/InstallThread.py
jdMinecraftLauncher/Languages.py
jdMinecraftLauncher/MicrosoftSecrets.py
jdMinecraftLauncher/Profile.py
jdMinecraftLauncher/ProfileCollection.py
jdMinecraftLauncher/ProfileImporter.py
jdMinecraftLauncher/RunMinecraft.py
jdMinecraftLauncher/Settings.py
jdMinecraftLauncher/Shortcut.py
jdMinecraftLauncher/__init__.py
jdMinecraftLauncher/jdMinecraftLauncher.py
jdMinecraftLauncher/secrets.json
jdMinecraftLauncher/version.txt
jdMinecraftLauncher/gui/LoginWindow.py
jdMinecraftLauncher/gui/ProfileWindow.py
jdMinecraftLauncher/gui/__init__.py
jdMinecraftLauncher/gui/MainWindow/AboutTab.py
jdMinecraftLauncher/gui/MainWindow/AccountTab.py
jdMinecraftLauncher/gui/MainWindow/FabricTab.py
jdMinecraftLauncher/gui/MainWindow/ForgeTab.py
jdMinecraftLauncher/gui/MainWindow/GameOutputTab.py
jdMinecraftLauncher/gui/MainWindow/MainWindow.py
jdMinecraftLauncher/gui/MainWindow/NewsTab.py
jdMinecraftLauncher/gui/MainWindow/OptionsTab.py
jdMinecraftLauncher/gui/MainWindow/ProfileEditorTab.py
jdMinecraftLauncher/gui/MainWindow/VersionEditorTab.py
jdMinecraftLauncher/gui/MainWindow/__init__.py
jdMinecraftLauncher/translations/jdMinecraftLauncher_de.qm
jdMinecraftLauncher/translations/jdMinecraftLauncher_es.qm
jdMinecraftLauncher/translations/jdMinecraftLauncher_he.qm
jdMinecraftLauncher/translations/jdMinecraftLauncher_nl.qm
jdMinecraftLauncher/translations/jdMinecraftLauncher_ru.qm
jdMinecraftLauncher/ui_compiled/AboutTab.py
jdMinecraftLauncher/ui_compiled/AccountTab.py
jdMinecraftLauncher/ui_compiled/MainWindow.py
jdMinecraftLauncher/ui_compiled/OptionsTab.py
jdMinecraftLauncher/ui_compiled/ProfileWindow.py
jdMinecraftLauncher/ui_compiled/__init__.py
jdMinecraftLauncher-6.2.dist-info/LICENSE
jdMinecraftLauncher-6.2.dist-info/METADATA
jdMinecraftLauncher-6.2.dist-info/WHEEL
jdMinecraftLauncher-6.2.dist-info/entry_points.txt
jdMinecraftLauncher-6.2.dist-info/top_level.txt
jdMinecraftLauncher-6.2.dist-info/RECORD
