Metadata-Version: 2.2
Name: jdMinecraftLauncher
Version: 6.2
Summary: A classic styled Minecraft Launcher
Author-email: JakobDev <jakobdev@gmx.de>
License: GPL v3
Project-URL: Source, https://codeberg.org/JakobDev/jdMinecraftLauncher
Project-URL: Issues, https://codeberg.org/JakobDev/jdMinecraftLauncher/issues
Project-URL: Translate, https://translate.codeberg.org/projects/jdMinecraftLauncher
Project-URL: Donation, https://ko-fi.com/jakobdev
Keywords: JakobDev,Minecraft,Mojang,launcher,PyQt
Classifier: Development Status :: 5 - Production/Stable
Classifier: Intended Audience :: End Users/Desktop
Classifier: Environment :: Other Environment
Classifier: Environment :: X11 Applications :: Qt
Classifier: License :: OSI Approved :: GNU General Public License v3 (GPLv3)
Classifier: Natural Language :: English
Classifier: Natural Language :: German
Classifier: Topic :: Games/Entertainment
Classifier: Operating System :: OS Independent
Classifier: Operating System :: POSIX
Classifier: Operating System :: POSIX :: Linux
Classifier: Operating System :: MacOS :: MacOS X
Classifier: Operating System :: Microsoft :: Windows
Classifier: Programming Language :: Python :: 3
Classifier: Programming Language :: Python :: 3.11
Classifier: Programming Language :: Python :: 3.12
Classifier: Programming Language :: Python :: 3 :: Only
Classifier: Programming Language :: Python :: Implementation :: CPython
Requires-Python: >=3.11
License-File: LICENSE
Requires-Dist: PyQt6
Requires-Dist: PyQt6-WebEngine
Requires-Dist: minecraft-launcher-lib
Requires-Dist: requests
Requires-Dist: feedparser
Provides-Extra: window-icon-progress-windows
Requires-Dist: PyTaskbarProgress; extra == "window-icon-progress-windows"
Provides-Extra: shortcut-linux
Requires-Dist: desktop-entry-lib; extra == "shortcut-linux"
